log21/__init__.py
log21/_argparse.py
log21/_module_helper.py
log21/argparse.py
log21/argumentify.py
log21/colors.py
log21/crash_reporter/__init__.py
log21/crash_reporter/formatters.py
log21/crash_reporter/reporters.py
log21/file_handler.py
log21/formatters.py
log21/levels.py
log21/logger.py
log21/logging_window.py
log21/manager.py
log21/pprint.py
log21/progress_bar.py
log21/stream_handler.py
log21/tree_print.py
log21-3.0.0.dist-info/WHEEL
log21-3.0.0.dist-info/METADATA
log21-3.0.0.dist-info/RECORD
