Metadata-Version: 2.3
Name: log21
Version: 3.0.0
Summary: A simple logging package
Keywords: python,log,colorize,color,logging,Python3,CodeWriter21
Author: CodeWriter21(Mehrad Pooryoussof)
Author-email: CodeWriter21(Mehrad Pooryoussof) <CodeWriter21@gmail.com>
License: Apache License 2.0
Classifier: Intended Audience :: Developers
Classifier: Programming Language :: Python :: 3
Classifier: Programming Language :: Python :: 3.9
Classifier: Programming Language :: Python :: 3.10
Classifier: Programming Language :: Python :: 3.11
Classifier: Programming Language :: Python :: 3.12
Classifier: Operating System :: Unix
Classifier: Operating System :: Microsoft :: Windows
Classifier: Operating System :: MacOS :: MacOS X
Requires-Dist: webcolors
Requires-Dist: docstring-parser
Requires-Python: >=3.9
Project-URL: Donations, https://github.com/MPCodeWriter21/log21/blob/master/DONATE.md
Project-URL: Homepage, https://github.com/MPCodeWriter21/log21
Project-URL: Source, https://github.com/MPCodeWriter21/log21
